ofonoctl/__init__.py
ofonoctl-0.4.1.dist-info/LICENSE
ofonoctl-0.4.1.dist-info/METADATA
ofonoctl-0.4.1.dist-info/WHEEL
ofonoctl-0.4.1.dist-info/entry_points.txt
ofonoctl-0.4.1.dist-info/top_level.txt
ofonoctl-0.4.1.dist-info/RECORD
